ldapdb/__init__.py
ldapdb/router.py
ldapdb/tests.py
ldapdb/version.py
ldapdb/backends/__init__.py
ldapdb/backends/ldap/__init__.py
ldapdb/backends/ldap/base.py
ldapdb/backends/ldap/compiler.py
ldapdb/models/__init__.py
ldapdb/models/base.py
ldapdb/models/fields.py
suap_django_ldapdb-1.5.3.dev1.dist-info/AUTHORS
suap_django_ldapdb-1.5.3.dev1.dist-info/LICENSE
suap_django_ldapdb-1.5.3.dev1.dist-info/METADATA
suap_django_ldapdb-1.5.3.dev1.dist-info/WHEEL
suap_django_ldapdb-1.5.3.dev1.dist-info/top_level.txt
suap_django_ldapdb-1.5.3.dev1.dist-info/RECORD
