Metadata-Version: 2.1
Name: suap-django-ldapdb
Version: 1.5.3.dev1
Summary: A fork from django-ldapdb
Home-page: https://github.com/ifrn-oficial/suap-django-ldapdb
Author: Diego Saraiva
Author-email: diegosaraiva@gmail.com
Maintainer: Diego Saraiva
Maintainer-email: diegosaraiva@gmail.com
License: BSD
Keywords: django,ldap,database,ldapdb
Classifier: Development Status :: 5 - Production/Stable
Classifier: Environment :: Web Environment
Classifier: Framework :: Django :: 3.0
Classifier: Framework :: Django :: 3.1
Classifier: Framework :: Django :: 4.1
Classifier: Framework :: Django :: 4.2
Classifier: Framework :: Django :: 5.0
Classifier: Framework :: Django :: 5.1
Classifier: Intended Audience :: Developers
Classifier: Intended Audience :: System Administrators
Classifier: License :: OSI Approved :: BSD License
Classifier: Programming Language :: Python
Classifier: Programming Language :: Python :: 3.6
Classifier: Programming Language :: Python :: 3.7
Classifier: Programming Language :: Python :: 3.8
Classifier: Programming Language :: Python :: 3.9
Classifier: Programming Language :: Python :: 3.10
Classifier: Programming Language :: Python :: 3.11
Classifier: Programming Language :: Python :: 3.12
Classifier: Topic :: Internet :: WWW/HTTP
Classifier: Topic :: System :: Systems Administration :: Authentication/Directory :: LDAP
Classifier: Topic :: Software Development :: Libraries :: Python Modules
Requires-Python: >=3.6
License-File: LICENSE
License-File: AUTHORS
Requires-Dist: Django >=2.2
Requires-Dist: python-ldap >=3.0
Provides-Extra: dev
Requires-Dist: check-manifest ; extra == 'dev'
Requires-Dist: flake8 ; extra == 'dev'
Requires-Dist: isort >=5.0.0 ; extra == 'dev'
Requires-Dist: tox ; extra == 'dev'
Requires-Dist: factory-boy ; extra == 'dev'
Requires-Dist: volatildap >=1.1.0 ; extra == 'dev'
Requires-Dist: wheel ; extra == 'dev'
Requires-Dist: zest.releaser[recommended] ; extra == 'dev'
